a2y_touch.cp312-win_amd64.pyd
a2y_touch-1.5.dist-info/LICENSE
a2y_touch-1.5.dist-info/METADATA
a2y_touch-1.5.dist-info/WHEEL
a2y_touch-1.5.dist-info/top_level.txt
a2y_touch-1.5.dist-info/RECORD
